Metadata-Version: 1.0
Name: capsicum
Version: 0.0.1
Summary: Lazy Event Risk Assessment Tool
Home-page: https://github.com/m-mizutani/capsicum
Author: Masayoshi Mizutani
Author-email: mizutani@sfc.wide.ad.jp
License: UNKNOWN
Platform: UNKNOWN
